basiclingua/__init__.py
basiclingua-2.0.0.dist-info/METADATA
basiclingua-2.0.0.dist-info/WHEEL
basiclingua-2.0.0.dist-info/top_level.txt
basiclingua-2.0.0.dist-info/RECORD
