Metadata-Version: 2.1
Name: basiclingua
Version: 2.0.0
Summary: A Python library based on various LLMs to perform basic and advanced natural language processing (NLP) tasks
Home-page: UNKNOWN
Author: Fareed Hassan Khan
Author-email: <fareedhassankhan12@gmail.com>
License: UNKNOWN
Keywords: python,NLP,Natural Language Processing,Linguistics,Gemini LLM,Google Gemini LLM
Platform: UNKNOWN
Classifier: Intended Audience :: Developers
Classifier: Programming Language :: Python :: 3
Classifier: License :: OSI Approved :: MIT License
Requires-Dist: google-generativeai
Requires-Dist: grpcio
Requires-Dist: grpcio-tools
Requires-Dist: openai
Requires-Dist: emoji
Requires-Dist: PyMuPDF
